{
  "term-one": [
    {
      "id": 1,
      "nameAr": " 1برمجة",
      "nameEn": "Programming 1",
      "navBar": ["references", "courses", "tools"],
      "courses": [
        {
          "nameFile": "Part 1",
          "urlFile": "https://drive.google.com/file/d/1P2HAA_H8G2kaum1ClxOWxeTqRAIbAwNc/view?usp=drive_link",
          "countPage": 14,
          "fileClass": "عملي"
        },
        {
          "nameFile": "Part 2",
          "urlFile": "https://drive.google.com/file/d/1jbYEmBE5N7gccb9FvIkvdJsxC-QtLAgF/view?usp=drive_link",
          "countPage": 11,
          "fileClass": "عملي"
        },
        {
          "nameFile": "Part 3",
          "urlFile": "https://drive.google.com/file/d/14EjKboL37XNXgHrI3HWCFn9iWhEdfYdB/view?usp=drive_link",
          "countPage": 10,
          "fileClass": "عملي"
        },
        {
          "nameFile": "Part 4",
          "urlFile": "https://drive.google.com/file/d/1jOxqIJtNKZiUbEt5rgST6thDU8vMMgFX/view?usp=drive_link",
          "countPage": 13,
          "fileClass": "عملي"
        },
        {
          "nameFile": "Part 5",
          "urlFile": "https://drive.google.com/file/d/1_54RxJ_tlM7-JrfkqNDbaVtyDyca2Qoi/view?usp=drive_link",
          "countPage": 5,
          "fileClass": "عملي"
        },
        {
          "nameFile": "Part 6",
          "urlFile": "https://drive.google.com/file/d/14N_8KA3rxNI9W9rH2oGE4dCYBPwxso-g/view?usp=drive_link",
          "countPage": 9,
          "fileClass": "عملي"
        },
        {
          "nameFile": "Part 7",
          "urlFile": "https://drive.google.com/file/d/1mT2-1UTG51M7jwNSmZktP6_CQSTu7Jgg/view?usp=drive_link",
          "countPage": 9,
          "fileClass": "عملي"
        },
        {
          "nameFile": "Part 8",
          "urlFile": "https://drive.google.com/file/d/1eYm8poAeHJT_Uk874mDWABChA4IDyz8Z/view?usp=drive_link",
          "countPage": 11,
          "fileClass": "عملي"
        },
        {
          "nameFile": "Part 9",
          "urlFile": "https://drive.google.com/file/d/15MZU-9tBj8SuKam3OFM7CBUpso8QenDV/view?usp=drive_link",
          "countPage": 4,
          "fileClass": "عملي"
        },
        {
          "nameFile": "Part 10",
          "urlFile": "https://drive.google.com/file/d/1Vc0wDK9phpG7kBsppPNgYMKr9rL5D3zd/view?usp=drive_link",
          "countPage": 4,
          "fileClass": "عملي"
        },
        {
          "nameFile": "Part 11",
          "urlFile": "https://drive.google.com/file/d/1jnMZGZxL6dCGMUxL8V9nKherAdq5BxCE/view?usp=drive_link",
          "countPage": 4,
          "fileClass": "عملي"
        },
        {
          "nameFile": "Passing arguments to functions",
          "urlFile": "https://drive.google.com/file/d/1fHw6UoDaoQJdmikliQNlZJVvq6VLNI8e/view?usp=drive_link",
          "countPage": 9,
          "fileClass": "عملي"
        },
        {
          "nameFile": "Part 1",
          "urlFile": "https://drive.google.com/file/d/1pYgbfX_310uViIoAzVPFLeyWLZsAmBBp/view?usp=drive_link",
          "countPage": 72,
          "fileClass": "نظري"
        },
        {
          "nameFile": "Part 2",
          "urlFile": "https://drive.google.com/file/d/1TQOjw95JLbZqPqwatrKS0fSl58aGXC2S/view?usp=drive_link",
          "countPage": 14,
          "fileClass": "نظري"
        }
      ],
      "tools": [
        {
          "name": "w3ch",
          "urlToll": "https://github.com/"
        },
        {
          "name": "w3ch",
          "urlToll": "https://github.com/"
        }
      ],
      "references": [
        {
          "name": "file 1",
          "urlFile": "https://github.com/",
          "countPage": 22
        },
        {
          "name": "file 2",
          "urlFile": "https://github.com/",
          "countPage": 22
        }
      ]
    },
    {
      "id": 2,
      "nameAr": " فيزياء",
      "nameEn": "Physics",
      "navBar": ["references", "courses", "tools"],
      "courses": [
        {
          "nameFile": "Part 1",
          "urlFile": "https://drive.google.com/file/d/1Nz8DxcKdZ-acaTa2o0iflm9b6QThKpZp/view?usp=drive_link",
          "countPage": 138,
          "fileClass": "نظري"
        },
        {
          "nameFile": "Summary",
          "urlFile": "https://drive.google.com/file/d/1_xhzH6z7yBt4WXMt0wtsyoP0ODX_nEb2/view?usp=drive_link",
          "countPage": 13,
          "fileClass": "نظري"
        }
      ]
    },
    {
      "id": 3,
      "nameAr": " تحليل 1",
      "nameEn": "Analysis 1",
      "navBar": ["references", "courses", "tools"],
      "courses": [
        {
          "nameFile": "Part 1",
          "urlFile": "https://drive.google.com/file/d/1kRtpTq3zhSmbhhdv2-gAJHkTHBS48TCe/view?usp=drive_link",
          "countPage": 108,
          "fileClass": "نظري"
        },
        {
          "nameFile": "Part 1",
          "urlFile": "https://drive.google.com/file/d/1aWDn4qQlP8JPuoNthG5NSryaPyg9XUTn/view?usp=drive_link",
          "countPage": 67,
          "fileClass": "عملي"
        }
      ]
    },
    {
      "id": 4,
      "nameAr": " جبر خطي",
      "nameEn": "Algebra",
      "navBar": ["references", "courses", "tools"],
      "courses": [
        {
          "nameFile": "Part 1",
          "urlFile": "https://drive.google.com/file/d/15JbtgEUw6Hg_YGS7X37O7teYM0bGrr_l/view?usp=drive_link",
          "countPage": 213,
          "fileClass": "نظري"
        },
        {
          "nameFile": "Summary",
          "urlFile": "https://drive.google.com/file/d/16-bgRQhEvY_o83_skzjs0cOcFIUeiloI/view?usp=drive_link",
          "countPage": 60,
          "fileClass": "نظري"
        }
      ]
    },
    {
      "id": 5,
      "nameAr": "مبادئ حاسوب",
      "nameEn": "Computer principles",
      "navBar": ["references", "courses", "tools"],
      "courses": [
        {
          "nameFile": "Part 1",
          "urlFile": "https://drive.google.com/file/d/1zfnGYe3-XuFTV_g8ydMsWiV-hbp2-3X0/view?usp=drive_link",
          "countPage": 187,
          "fileClass": "نظري"
        }
      ]
    },
    {
      "id": 6,
      "nameAr": "1 عربي",
      "nameEn": "Arabic 1",
      "navBar": ["references", "courses", "tools"],
      "courses": [
        {
          "nameFile": "Part 1",
          "urlFile": "https://drive.google.com/file/d/11irfpHZqcRedsgcrr0GRjUKpR-Yo_uBg/view?usp=drive_link",
          "countPage": 98,
          "fileClass": "نظري"
        }
      ],
      "CQ": [
        {
          "nameFile": "Part 1",
          "urlFile": "https://drive.google.com/file/d/1Drmd84DvBzAYILUX25s39y6gemen_GEF/view?usp=drive_link",
          "countPage": 3
        }
      ]
    },
    {
      "id": 7,
      "nameAr": "1  لغة انكليزية",
      "nameEn": "English 1",
      "navBar": ["references", "courses", "tools"],
      "courses": [
        {
          "nameFile": "مقرر 1",
          "urlFile": "https://drive.google.com/file/d/1HrAvWOeh_w3HpQ6h2Lh-sU7_GmDC2ZCr/view?usp=drive_link",
          "countPage": 101,
          "fileClass": "نظري"
        },
        {
          "nameFile": "ملخص مطلوبات 1",
          "urlFile": "https://drive.google.com/file/d/19ARwU5jAFnACWJ2xF-OjMF9q8NBShw1Y/view?usp=drive_link",
          "countPage": 101,
          "fileClass": "نظري"
        }
      ]
    }
  ],
  
    "term-two": [
      {
        "id": 8,
        "nameAr": "2 برمجة",
        "nameEn": "Programming2",
        "navBar": ["references", "courses", "tools"],
        "courses": [
          {
            "nameFile": "الجلسة الاولى",
            "urlFile": "https://drive.google.com/file/d/1IO5E-O7TUYc3GAC9octPhyMNvW-FFp2k/view?usp=drive_link",
            "countPage": 22,
            "fileClass": "عملي"
          },
          {
            "nameFile": "الجلسة الثانية",
            "urlFile": "https://drive.google.com/file/d/13sVW_42QRjPGGP1t44gc6RQQIqF7SeXc/view?usp=drive_link",
            "countPage": 22,
            "fileClass": "عملي"
          },
          {
            "nameFile": "الجلسة الثالثة",
            "urlFile": "https://drive.google.com/file/d/1F6yMfhOK996T6mXfvU-HsybshZUR2Oyg/view?usp=drive_link",
            "countPage": 22,
            "fileClass": "عملي"
          },
          {
            "nameFile": "الجلسة الرابعه",
            "urlFile": "https://drive.google.com/file/d/1sUqCdiebA-PYkl4UjOJl9EtUlsm_cETS/view?usp=drive_link",
            "countPage": 22,
            "fileClass": "عملي"
          },
          {
            "nameFile": "الجلسة الخامسة",
            "urlFile": "https://drive.google.com/file/d/1Dg-p31QJZWNJb60J1PVqcJqE0Cf1T0nR/view?usp=drive_link",
            "countPage": 22,
            "fileClass": "عملي"
          },
          {
            "nameFile": "الجلسة السادسة",
            "urlFile": "https://drive.google.com/file/d/19utzWAMy9ZU3o4aE81qigZGQdYY-S78p/view?usp=drive_link",
            "countPage": 22,
            "fileClass": "عملي"
          },
          {
            "nameFile": "الجلسة السابعه",
            "urlFile": "https://drive.google.com/file/d/14ZsCudykq_rqK3wbnGR34ZkPUrrhCs7B/view?usp=drive_link",
            "countPage": 22,
            "fileClass": "عملي"
          },
          {
            "nameFile": "الجلسة الثامنة",
            "urlFile": "https://drive.google.com/file/d/1Pgw7bTkiwKZddmuji7NaGkYSthWRWhvh/view?usp=drive_link",
            "countPage": 22,
            "fileClass": "عملي"
          },
          {
            "nameFile": "الجلسة التاسعه",
            "urlFile": "https://drive.google.com/file/d/1x3aCA2xqkZ3AUneRN_6DrSCc6LIsKfLb/view?usp=drive_link",
            "countPage": 22,
            "fileClass": "عملي"
          },
          {
            "nameFile": "الجلسة العاشرة",
            "urlFile": "https://drive.google.com/file/d/1cpaINc9LXDabFEKtM9shI56PCKSaTYzT/view?usp=drive_link",
            "countPage": 22,
            "fileClass": "عملي"
          },
          {
            "nameFile": "المقرر",
            "urlFile": "https://drive.google.com/file/d/1xKco4AZzVAAY4xA66VS-2HFYA0aesM6p/view?usp=drive_link",
            "countPage": 22,
            "fileClass": "نظري"
          }
        ],
        "tools": [
          {
            "name": "w3ch",
            "urlTool": "https://github.com/"
          }
        ],
        "references": [
          {
            "name": "file 1",
            "urlFile": "https://github.com/",
            "countPage": 22
          },
          {
            "name": "file 2",
            "urlFile": "https://github.com/",
            "countPage": 22
          }
        ]
      },
      {
        "id": 9,
        "nameAr": "2 تحليل",
        "nameEn": "analyses 2",
        "navBar": ["references", "courses", "tools"],
        "courses": [
          {
            "name": "مقرر",
            "urlFile": "https://drive.google.com/file/d/1O7zmEGLdYn_25kpWeUXg8sg95kXRMGvk/view?usp=drive_link",
            "countPage": 141,
            "fileClass": "عملي - نظري"
          }
        ],
        "tools": [
          {
            "name": "w3ch",
            "urlTool": "https://github.com/"
          }
        ],
        "references": [
          {
            "name": "تكاملات",
            "urlFile": "https://youtu.be/3m3t0akVJ2c?si=6yDSVx_WwPCLOQ22",
            "videos": 11
          },
          {
            "name": "file 2",
            "urlFile": "https://github.com/",
            "countPage": 22
          }
        ]
      },
      {
        "id": 10,
        "nameAr": "برمجة ويب 1",
        "nameEn": "web programming 1",
        "navBar": ["references", "courses", "tools"],
        "courses": [
          {
            "nameFile": "جلسة 1",
            "urlFile": "https://drive.google.com/file/d/18P5SmFlEzMW95QtGVgtMLCCuM5Q98dG0/view?usp=drive_link",
            "countPage": 27,
            "fileClass": "عملي"
          },
          {
            "nameFile": "جلسة 2",
            "urlFile": "https://drive.google.com/file/d/1g2dNROGeix2kW1oUblASotgyznWu05wa/view?usp=drive_link",
            "countPage": 17,
            "fileClass": "عملي"
          },
          {
            "nameFile": "جلسة 3",
            "urlFile": "https://drive.google.com/file/d/1cXYm-I9J_7SuKf7fveq53-7Aquuo0S5x/view?usp=drive_link",
            "countPage": 8,
            "fileClass": "عملي"
          },
          {
            "nameFile": "جلسة 4",
            "urlFile": "https://drive.google.com/file/d/1342_N5jwtygZkX7EKLgU4cPnPeZjN_e9/view?usp=drive_link",
            "countPage": 12,
            "fileClass": "عملي"
          },
          {
            "nameFile": "جلسة 5-6",
            "urlFile": "https://drive.google.com/file/d/1F7xXhYAU7QT52_8cC1ZkhWkZhaBAcb86/view?usp=drive_link",
            "countPage": 27,
            "fileClass": "عملي"
          },
          {
            "nameFile": "جلسة 7",
            "urlFile": "https://drive.google.com/file/d/1dz2OqzDjVO7Q72NVHeN0bjc6Hd7eHobP/view?usp=drive_link",
            "countPage": 24,
            "fileClass": "عملي"
          },
          {
            "nameFile": "جلسة 8",
            "urlFile": "https://drive.google.com/file/d/1b6wn-O_1J_2xIZeD3g7uRhXC5Y_qEsst/view?usp=drive_link",
            "countPage": 18,
            "fileClass": "عملي"
          },
          {
            "nameFile": "جلسة 9",
            "urlFile": "https://drive.google.com/file/d/11HV1Ki2ItmnqJdraI8O0Z7GtAA-A-VYS/view?usp=drive_link",
            "countPage": 19,
            "fileClass": "عملي"
          },
          {
            "nameFile": "جلسة 10-11",
            "urlFile": "https://drive.google.com/file/d/1wP4VeJe1pVzaZCXDnJqe95Ay2UHfPbGl/view?usp=drive_link",
            "countPage": 14,
            "fileClass": "عملي"
          }
        ],
        "tools": [
          {
            "name": "w3ch",
            "urlTool": "https://github.com/"
          }
        ],
        "references": [
          {
            "name": "Html",
            "urlFile": "https://youtu.be/6QAELgirvjs?si=LHG8dGIgWcIavy5Q",
            "videos": 37
          },
          {
            "name": "CSS Course",
            "urlFile": "https://youtu.be/X1ulCwyhCVM?si=_uzGlPBFRkHJUJB9",
            "videos": 88
          },
          {
            "name": "JAVA SCRIPT Course",
            "urlFile": "https://youtu.be/GM6dQBmc-Xg?si=KtKDqBifA94Mctan",
            "videos": 188
          }
        ]
      },
      {
        "id": 11,
        "nameAr": "ثقافة وحضارة",
        "nameEn": "culture",
        "navBar": ["references", "courses", "tools"],
        "courses": [
          {
            "nameFile": "ثقافة وحضارة",
            "urlFile": "https://drive.google.com/file/d/1_qhi8aqJduiv8j0KAUnOzfPhDAnQDB_e/view?usp=drive_link",
            "countPage": 90,
            "fileClass": "نظري"
          },
          {
            "nameFile": "ملخص ثقافة وحضارة 1",
            "urlFile": "https://drive.google.com/file/d/1IH3v8C1SoNexSlDoVKX4YmVotALhLr_-/view?usp=drive_link",
            "countPage": 12,
            "fileClass": "ملخص"
          },
          {
            "nameFile": "ملخص ثقافة وحضارة 2",
            "urlFile": "https://drive.google.com/file/d/1IH3v8C1SoNexSlDoVKX4YmVotALhLr_-/view?usp=drive_link",
            "countPage": 12,
            "fileClass": "ملخص"
          }
        ],
        "tools": [
          {
            "name": "w3ch",
            "urlTool": "https://github.com/"
          }
        ],
        "references": [
          {
            "name": "file 1",
            "urlFile": "https://github.com/",
            "countPage": 22
          },
          {
            "name": "file 2",
            "urlFile": "https://github.com/",
            "countPage": 22
          }
        ]
      },
      {
        "id": 12,
        "nameAr": "دارات كهربائية",
        "nameEn": "Electrical-circuits",
        "navBar": ["references", "courses", "tools"],
        "courses": [
          {
            "nameFile": "مقرر الدارات",
            "urlFile": "https://drive.google.com/file/d/197GlIlGpb_BrHMBCWge2RRzEGmlOVwI3/view?usp=drive_link",
            "countPage": 83,
            "fileClass": "نظري"
          },
          {
            "nameFile": "ورقة عمل",
            "urlFile": "https://drive.google.com/file/d/1jJa7fJ-1F2JsXxr-lj4RGg1htcmDWGgx/view?usp=drive_link",
            "countPage": 1,
            "fileClass": "عملي"
          },
          {
            "nameFile": "تجربة قانون كيرشوف الأول + الثاني",
            "urlFile": "https://drive.google.com/file/d/1oTbx9Vb28M4k3FMKroGa7ksnLUN4TSB9/view?usp=drive_link",
            "countPage": 3,
            "fileClass": "عملي"
          },
          {
            "nameFile": "التجربة الثانية _ وقانون أوم",
            "urlFile": "https://drive.google.com/file/d/1DZzDewI2FEWE8l7ldQuTCiUYk7ho3yJJ/view?usp=drive_link",
            "countPage": 3,
            "fileClass": "عملي"
          },
          {
            "nameFile": "أدوات الدارات",
            "urlFile": "https://drive.google.com/file/d/1dxtV-RgIJUps-k5FcFe4XmBWR4kxkI9P/view?usp=drive_link",
            "countPage": 3,
            "fileClass": "عملي"
          }
        ],
        "tools": [
          {
            "name": "w3ch",
            "urlTool": "https://github.com/"
          }
        ],
        "references": [
          {
            "name": "file 1",
            "urlFile": "https://github.com/",
            "countPage": 22
          },
          {
            "name": "file 2",
            "urlFile": "https://github.com/",
            "countPage": 22
          }
        ]
      },
      {
        "id": 13,
        "nameAr": "احتمالات وااحصاء",
        "nameEn": "statistics",
        "navBar": ["references", "courses", "tools"],
        "courses": [
          {
            "nameFile": "احتمالات وااحصاء",
            "urlFile": "https://drive.google.com/file/d/1nVRxe-8TDat7sT_xAwxc2BP10xVQWbDZ/view?usp=drive_link",
            "countPage": 101,
            "fileClass": "نظري - عملي"
          }
        ],
        "tools": [
          {
            "name": "w3ch",
            "urlTool": "https://github.com/"
          }
        ],
        "references": [
          {
            "nameFile": "file 1",
            "urlFile": "https://github.com/",
            "countPage": 22
          },
          {
            "nameFile": "file 2",
            "urlFile": "https://github.com/",
            "countPage": 22
          }
        ]
      },
      {
        "id": 14,
        "nameAr": "لغة انجليزي 2",
        "nameEn": "English 2",
        "navBar": ["references", "courses", "tools"],
        "courses": [
          {
            "nameFile": "مقرر",
            "urlFile": "https://drive.google.com/file/d/1HrAvWOeh_w3HpQ6h2Lh-sU7_GmDC2ZCr/view?usp=drive_link",
            "countPage": 60,
            "fileClass": "نظري"
          },
          {
            "nameFile": "دورات",
            "urlFile": "https://drive.google.com/file/d/1P-LXb3lJutr27Gw1CXNLboPsYYKUMulY/view?usp=drive_link",
            "countPage": 14,
            "fileClass": "عملي"
          }
        ],
        "tools": [
          {
            "name": "w3ch",
            "urlTool": "https://github.com/"
          }
        ],
        "references": [
          {
            "name": "file 1",
            "urlFile": "https://github.com/",
            "countPage": 22
          },
          {
            "name": "file 2",
            "urlFile": "https://github.com/",
            "countPage": 22
          }
        ]
      }
    ]
  ,
  "tests": []
}
